mecher_appium_page/__init__.py
mecher_appium_page/appium_page_class.py
mecher_appium_page/models/__init__.py
mecher_appium_page/models/app_config.py
mecher_appium_page/models/locators.py
mecher_appium_page-0.1.0.dist-info/METADATA
mecher_appium_page-0.1.0.dist-info/WHEEL
mecher_appium_page-0.1.0.dist-info/top_level.txt
mecher_appium_page-0.1.0.dist-info/RECORD
