Metadata-Version: 2.1
Name: mecher_appium_page
Version: 0.1.0
Summary: Universal Appium Page
Home-page: https://github.com/MaximChernyak98/mecher_appium_page
Maintainer: mecher
Keywords: testing
Requires-Dist: Appium-Python-Client==3.2.1
Requires-Dist: allure-pytest==2.13.5
